flox/__init__.py
flox/_version.py
flox/aggregate_flox.py
flox/aggregate_npg.py
flox/aggregate_numbagg.py
flox/aggregations.py
flox/cache.py
flox/core.py
flox/py.typed
flox/visualize.py
flox/xarray.py
flox/xrdtypes.py
flox/xrutils.py
flox-9.11.dist-info/LICENSE
flox-9.11.dist-info/METADATA
flox-9.11.dist-info/WHEEL
flox-9.11.dist-info/top_level.txt
flox-9.11.dist-info/RECORD
