Metadata-Version: 2.1
Name: flox
Version: 9.11
Summary: GroupBy operations for dask.array
License: Apache License
Project-URL: homepage, https://flox.readthedocs.io
Project-URL: documentation, https://flox.readthedocs.io
Project-URL: repository, https://github.com/xarray-contrib/flox.git
Project-URL: changelog, https://github.com/xarray-contrib/flox/releases
Keywords: xarray,dask,groupby
Classifier: Development Status :: 4 - Beta
Classifier: License :: OSI Approved :: Apache Software License
Classifier: Natural Language :: English
Classifier: Operating System :: OS Independent
Classifier: Programming Language :: Python
Classifier: Programming Language :: Python :: 3.10
Classifier: Programming Language :: Python :: 3.11
Classifier: Programming Language :: Python :: 3.12
Requires-Python: >=3.10
License-File: LICENSE
Requires-Dist: pandas >=1.5
Requires-Dist: packaging >=21.3
Requires-Dist: numpy >=1.22
Requires-Dist: numpy-groupies >=0.9.19
Requires-Dist: toolz
Requires-Dist: scipy >=1.9
Provides-Extra: all
Requires-Dist: cachey ; extra == 'all'
Requires-Dist: dask ; extra == 'all'
Requires-Dist: numba ; extra == 'all'
Requires-Dist: numbagg ; extra == 'all'
Requires-Dist: xarray ; extra == 'all'
Provides-Extra: test
Requires-Dist: netCDF4 ; extra == 'test'
